douzone_crawl/__init__.py
douzone_crawl/cli.py
douzone_crawl/crawl.py
douzone_crawl-0.2.0.dist-info/METADATA
douzone_crawl-0.2.0.dist-info/WHEEL
douzone_crawl-0.2.0.dist-info/top_level.txt
douzone_crawl-0.2.0.dist-info/RECORD
