Metadata-Version: 2.2
Name: douzone_crawl
Version: 0.2.0
Summary: 효율적인 웹 크롤링 및 검색 결과 처리를 위한 라이브러리
Home-page: https://github.com/zozni-douzone/douzone_crawl.git
Author: choheejin
Author-email: choheejin <hjcho1027@douzone.com>
Classifier: Programming Language :: Python :: 3
Classifier: License :: OSI Approved :: MIT License
Classifier: Operating System :: OS Independent
Requires-Python: >=3.12
Requires-Dist: selenium>=4.0.0
Requires-Dist: python-dotenv>=0.19.0
Dynamic: author
Dynamic: home-page
Dynamic: requires-python
